{
  "id": 4854,
  "name": "PY Eb 173",
  "site": "PY",
  "transliteration": "_____ pa-ra-]ko , e-ke-qe , ka-ma , ko-to-no-k°o°[ _________________ e-o to-so-de pe-mo GRA 1 po-so-]re-ja , te-o-jo , do-e-ra ,° e-ke-qe , o-na-to , pa-r°o°[ pa-ra-ko to-so-de pe-mo GRA T 1 V 3",
  "words": [
    "para",
    "ko",
    "ekeqe",
    "kama",
    "kotonok",
    "eo",
    "tosode",
    "pemo",
    "poso",
    "reja",
    "teojo",
    "doera",
    "ekeqe",
    "onato",
    "par",
    "parako",
    "tosode",
    "pemo"
  ]
}
