{
  "corpus_link": "https://cefael.efa.gr/detail.php?site_id=1&amp;actionID=page&amp;serie_id=EtCret&amp;volume_number=21&amp;issue_number=3&amp;ce=540ecor2uudeumpibfksblm7ss9s2lsi&amp;sp=34",
  "dimensions": "5.5 cm × 10.1 cm × 1.25 cm",
  "fetched_at": "2026-05-04T00:00:00Z",
  "genre_hint": "accountancy",
  "id": "ARKH 3b",
  "kind_raw": "Tablet",
  "n_signs": 9,
  "n_words": 2,
  "period": "LM I",
  "raw_transliteration": "[?]-AB57-AB39 / LOG:AB120 / AB39-A314 / LOG:AB120 / LOG:AB302 / LOG:AB131a",
  "site": "Arkhanes",
  "source": "sigla:document/ARKH%203b/",
  "source_url": "https://sigla.phis.me/document/ARKH%203b/",
  "support": "tablet",
  "tokens": [
    "[?]",
    "AB57",
    "AB39",
    "DIV",
    "LOG:AB120",
    "DIV",
    "AB39",
    "A314",
    "DIV",
    "LOG:AB120",
    "DIV",
    "LOG:AB302",
    "DIV",
    "LOG:AB131a"
  ],
  "transcription_confidence": "partial"
}
