{
  "corpus_link": "https://cefael.efa.gr/detail.php?site_id=1&amp;actionID=page&amp;serie_id=EtCret&amp;volume_number=21&amp;issue_number=1&amp;ce=540ecor2uudeumpibfksblm7ss9s2lsi&amp;sp=114",
  "dimensions": "5.1 cm × 3.3 cm × 0.8 cm",
  "fetched_at": "2026-05-04T00:00:00Z",
  "genre_hint": "accountancy",
  "id": "HT 41a",
  "kind_raw": "Tablet",
  "n_signs": 13,
  "n_words": 3,
  "period": "LM IB",
  "raw_transliteration": "AB78-AB69 / A305 / LOG:A304 / AB27 / LOG:A304 / AB73-AB01-AB30 / AB03-AB57 / FRAC:A703 / FRAC:A703",
  "site": "Haghia Triada",
  "source": "sigla:document/HT%2041a/",
  "source_url": "https://sigla.phis.me/document/HT%2041a/",
  "support": "tablet",
  "tokens": [
    "AB78",
    "AB69",
    "DIV",
    "A305",
    "DIV",
    "LOG:A304",
    "DIV",
    "AB27",
    "DIV",
    "LOG:A304",
    "DIV",
    "AB73",
    "AB01",
    "AB30",
    "DIV",
    "AB03",
    "AB57",
    "DIV",
    "FRAC:A703",
    "DIV",
    "FRAC:A703"
  ],
  "transcription_confidence": "clean"
}
