{
  "corpus_link": "https://cefael.efa.gr/detail.php?site_id=1&amp;actionID=page&amp;serie_id=EtCret&amp;volume_number=21&amp;issue_number=1&amp;ce=540ecor2uudeumpibfksblm7ss9s2lsi&amp;sp=294",
  "dimensions": "4.6 cm × 4.7 cm × 1 cm",
  "fetched_at": "2026-05-04T00:00:00Z",
  "genre_hint": "accountancy",
  "id": "KN 2",
  "kind_raw": "Tablet",
  "n_signs": 4,
  "n_words": 1,
  "period": "LM IA",
  "raw_transliteration": "AB26-AB06 / LOG:AB118 / LOG:A519",
  "site": "Knossos",
  "source": "sigla:document/KN%202/",
  "source_url": "https://sigla.phis.me/document/KN%202/",
  "support": "tablet",
  "tokens": [
    "AB26",
    "AB06",
    "DIV",
    "LOG:AB118",
    "DIV",
    "LOG:A519"
  ],
  "transcription_confidence": "clean"
}
